{
 "cards": [
  {
   "hidden": 0,
   "label": "School  & Departments",
   "links": "[\n    {\n        \"description\": \"School Organization.\",\n        \"label\": \"School\",\n        \"name\": \"School\",\n        \"type\": \"doctype\"\n    },\n    {\n        \"description\": \"The various dpt. withing the school.\",\n        \"label\": \"Department\",\n        \"name\": \"Department\",\n        \"type\": \"doctype\"\n    }, \n    {\n        \"description\": \"Location, The map of your school.\",\n        \"label\": \"Location\",\n        \"name\": \"Location\",\n        \"type\": \"doctype\"\n    }     \n]"
  },
  {
   "hidden": 0,
   "label": "Years & Terms",
   "links": "[\n    {\n        \"description\": \"Setting up the academic year\",\n        \"label\": \"Academic Year\",\n        \"name\": \"Academic Year\",\n        \"type\": \"doctype\"\n    }, \n    {\n        \"description\": \"Setting up the academic terms\",\n        \"label\": \"Academic Term\",\n        \"name\": \"Academic Term\",\n        \"type\": \"doctype\"\n    }, \n    {\n        \"description\": \"Setting up the holidays list\",\n        \"label\": \"School Calendar\",\n        \"name\": \"School Calendar\",\n        \"type\": \"doctype\"\n    }\n]"
  },
  {
   "hidden": 0,
   "label": "Collaboration",
   "links": "[\n    {\n        \"description\": \"Meetings organized at school\",\n        \"label\": \"Meeting\",\n        \"name\": \"Meeting\",\n        \"type\": \"doctype\"\n    }, \n    {\n        \"description\": \"Your Todo list\",\n        \"label\": \"Todo list\",\n        \"name\": \"ToDo\",\n        \"type\": \"doctype\"\n    }, \n    {\n        \"description\": \"Your School Event List\",\n        \"label\": \"School Events\",\n        \"name\": \"School Event\",\n        \"type\": \"doctype\"\n    }\n    \n]"
  },
  {
   "hidden": 0,
   "label": "School Settings",
   "links": "[\n    {\n        \"description\": \"Setting up current parameters for the school\",\n        \"label\": \"Education Settings\",\n        \"name\": \"Education Settings\",\n        \"type\": \"doctype\"\n    }, \n    {\n        \"description\": \"Fine Tuning Privacy settings\",\n        \"label\": \"Privacy Settings\",\n        \"name\": \"Privacy Settings\",\n        \"type\": \"doctype\"\n    }, \n    {\n        \"description\": \"School Student Admission\",\n        \"label\": \"Student Admission\",\n        \"name\": \"Student Admission\",\n        \"type\": \"doctype\"\n    }      \n]"
  },
  {
   "hidden": 0,
   "label": "Assets",
   "links": "[\n    {\n        \"description\": \"Storage\",\n        \"label\": \"Storage\",\n        \"name\": \"Storage\",\n        \"type\": \"doctype\"\n    }, \n    {\n        \"description\": \"Item\",\n        \"label\": \"Item\",\n        \"name\": \"Items\",\n        \"type\": \"doctype\"\n    }, \n    {\n        \"description\": \"Storage Type\",\n        \"label\": \"Storage Type\",\n        \"name\": \"Storage Type\",\n        \"type\": \"doctype\"\n    }       \n]"
  }
 ],
 "category": "Modules",
 "charts": [],
 "charts_label": "",
 "creation": "2020-09-13 22:21:28.407928",
 "developer_mode_only": 0,
 "disable_user_customization": 1,
 "docstatus": 0,
 "doctype": "Desk Page",
 "extends_another_page": 0,
 "hide_custom": 0,
 "idx": 0,
 "is_default": 0,
 "is_standard": 1,
 "label": "School Settings",
 "modified": "2021-03-13 11:37:41.178511",
 "modified_by": "Administrator",
 "module": "School Settings",
 "name": "School Settings",
 "owner": "Administrator",
 "pin_to_bottom": 0,
 "pin_to_top": 0,
 "shortcuts": [
  {
   "doc_view": "Tree",
   "label": "School",
   "link_to": "School",
   "type": "DocType"
  },
  {
   "doc_view": "Calendar",
   "label": "School Event",
   "link_to": "School Event",
   "type": "DocType"
  },
  {
   "doc_view": "Dashboard",
   "label": "School Dashboard",
   "link_to": "School Dashboard",
   "type": "Dashboard"
  }
 ]
}