{
 "actions": [],
 "creation": "2021-05-27 13:49:42.670265",
 "doctype": "DocType",
 "editable_grid": 1,
 "engine": "InnoDB",
 "field_order": [
  "participant",
  "participant_name"
 ],
 "fields": [
  {
   "fieldname": "participant",
   "fieldtype": "Link",
   "ignore_user_permissions": 1,
   "in_list_view": 1,
   "in_standard_filter": 1,
   "label": "Participant",
   "options": "User",
   "reqd": 1
  },
  {
   "fetch_from": "participant.full_name",
   "fieldname": "participant_name",
   "fieldtype": "Read Only",
   "ignore_user_permissions": 1,
   "in_list_view": 1,
   "label": "Participant Name",
   "reqd": 1
  }
 ],
 "index_web_pages_for_search": 1,
 "istable": 1,
 "links": [],
 "modified": "2021-05-27 13:49:42.670265",
 "modified_by": "Administrator",
 "module": "School Settings",
 "name": "School Event Participant",
 "owner": "Administrator",
 "permissions": [],
 "quick_entry": 1,
 "sort_field": "modified",
 "sort_order": "DESC",
 "track_changes": 1
}